CHANGES.txt
LICENSE.txt
MANIFEST.in
README.rst
setup.py
filerotate/__init__.py
filerotate/__main__.py
filerotate/__version__.py
filerotate.egg-info/PKG-INFO
filerotate.egg-info/SOURCES.txt
filerotate.egg-info/dependency_links.txt
filerotate.egg-info/entry_points.txt
filerotate.egg-info/top_level.txt