Metadata-Version: 1.0
Name: filerotate
Version: 1.0.3
Summary: Rotate filenames
Home-page: UNKNOWN
Author: Alen Mujezinovic
Author-email: flashingpumpkin@gmail.com
License: UNKNOWN
Platform: UNKNOWN
